MANIFEST.in
setup.py
django_fancy_apps.egg-info/PKG-INFO
django_fancy_apps.egg-info/SOURCES.txt
django_fancy_apps.egg-info/dependency_links.txt
django_fancy_apps.egg-info/not-zip-safe
django_fancy_apps.egg-info/requires.txt
django_fancy_apps.egg-info/top_level.txt
fancy/__init__.py
fancy/blog/__init__.py
fancy/blog/admin.py
fancy/blog/admin_forms.py
fancy/blog/feeds.py
fancy/blog/models.py
fancy/blog/settings.py
fancy/blog/sitemap.py
fancy/blog/urls.py
fancy/blog/views.py
fancy/blog/management/__init__.py
fancy/blog/management/commands/__init__.py
fancy/blog/management/commands/import.py
fancy/events/__init__.py
fancy/events/admin.py
fancy/events/models.py
fancy/events/urls.py
fancy/events/views.py
fancy/events/locale/tr/LC_MESSAGES/django.mo
fancy/events/locale/tr/LC_MESSAGES/django.po
fancy/events/templates/admin/events/location/change_form.html
fancy/gallery/__init__.py
fancy/gallery/admin.py
fancy/gallery/helpers.py
fancy/gallery/models.py
fancy/gallery/parser.py
fancy/gallery/settings.py
fancy/gallery/urls.py
fancy/gallery/views.py
fancy/gallery/widgets.py
fancy/gallery/locale/tr/LC_MESSAGES/django.mo
fancy/gallery/locale/tr/LC_MESSAGES/django.po
fancy/gallery/static/admin/imageinline.js
fancy/gallery/templates/admin/gallery/image/change_form.html
fancy/gallery/templates/admin/gallery/image/inline.html
fancy/gallery/templates/fancy/gallery/album_index.html
fancy/gallery/templates/fancy/gallery/inline_album.html
fancy/gallery/templatetags/__init__.py
fancy/gallery/templatetags/gallery.py
fancy/mailform/__init__.py
fancy/mailform/settings.py
fancy/mailform/urls.py
fancy/mailform/views.py
fancy/mailform/templates/fancy/mailform/default.html
fancy/mailform/templates/fancy/mailform/mail/default.html
fancy/mailform/templatetags/__init__.py
fancy/mailform/templatetags/mailform.py
fancy/pages/__init__.py
fancy/pages/admin.py
fancy/pages/admin_forms.py
fancy/pages/context_processors.py
fancy/pages/models.py
fancy/pages/settings.py
fancy/pages/sitemap.py
fancy/pages/urls.py
fancy/pages/views.py
fancy/pages/locale/tr_TR/LC_MESSAGES/django.mo
fancy/pages/locale/tr_TR/LC_MESSAGES/django.po
fancy/pages/management/__init__.py
fancy/pages/management/commands/__init__.py
