Metadata-Version: 1.1
Name: django-fancy-apps
Version: 0.1.6
Summary: Django Fancy Apps
Home-page: http://github.com/muratcorlu/django-fancy-apps
Author: Murat Çorlu
Author-email: muratcorlu@gmail.com
License: MIT
Platform: UNKNOWN
Classifier: Environment :: Web Environment
Classifier: Framework :: Django
Classifier: Operating System :: OS Independent
Classifier: Programming Language :: Python
